math_lihu_4375/__init__.py
math_lihu_4375-0.1.0.dist-info/WHEEL
math_lihu_4375-0.1.0.dist-info/entry_points.txt
math_lihu_4375-0.1.0.dist-info/METADATA
math_lihu_4375-0.1.0.dist-info/RECORD
